{
  "buy_now": [
    "Buy Now",
    "Purchase Now",
    "Order Now",
    "Quick Buy",
    "Instant Purchase",
    "Buy Direct",
    "Purchase Direct",
    "Checkout Now",
    "Express Buy",
    "Direct Order"
  ],
  "search_placeholder": [
    "Search Autozone",
    "Find products",
    "Search for items",
    "What are you looking for?",
    "Type to search",
    "Search our store",
    "Enter search term",
    "Product lookup",
    "Find what you need",
    "Search catalog"
  ],
  "checkout": [
    "Checkout",
    "Proceed to Checkout",
    "Complete Order",
    "Finalize Purchase",
    "Go to Checkout",
    "Pay Now",
    "Complete Payment",
    "Confirm Order",
    "Process Order",
    "Order Now"
  ],
  "continue_shopping": [
    "Continue Shopping",
    "Keep Shopping",
    "Back to Shop",
    "Shop More",
    "Return to Store",
    "Browse More",
    "More Products",
    "Find More",
    "Continue Browse",
    "Shop Again"
  ],
  "in_stock": [
    "In stock",
    "Available",
    "Ready to ship",
    "In stock now",
    "Available now",
    "On hand",
    "Ready",
    "Stock available",
    "Ships soon",
    "In inventory"
  ],
  "remove": [
    "Remove",
    "Delete",
    "Remove Item",
    "Discard",
    "Take Out",
    "Clear",
    "Eliminate",
    "Drop",
    "Erase",
    "Exclude"
  ],
  "quantity": [
    "Quantity",
    "Qty",
    "Amount",
    "Count",
    "Number",
    "Qty Required",
    "Pieces",
    "Units",
    "Item Count",
    "Quantity Needed"
  ],
  "add_to_cart": [
    "Add to Cart",
    "Add to Basket",
    "Add Item",
    "Put in Cart",
    "Include in Cart",
    "Add to Bag",
    "Insert to Cart",
    "Place in Cart",
    "Move to Cart",
    "Append to Cart"
  ],
  "price": [
    "Price",
    "Cost",
    "Price Tag",
    "Value",
    "Amount",
    "Item Price",
    "Unit Cost",
    "Retail Price",
    "Sale Price",
    "List Price"
  ],
  "account_greeting": [
    "Hello, user",
    "Hi there",
    "Welcome back",
    "Hey user",
    "Good day",
    "Hello shopper",
    "Greetings",
    "Welcome user",
    "Hi customer",
    "Hello member"
  ],
  "search_button": [
    "Search",
    "Go",
    "Find",
    "Submit",
    "Look up",
    "Search Now",
    "Execute",
    "Query",
    "Lookup",
    "Seek"
  ],
  "total": [
    "Total",
    "Sum",
    "Total Cost",
    "Grand Total",
    "Final Total",
    "Order Total",
    "Subtotal",
    "Cart Total",
    "Sum Total",
    "Total Amount"
  ],
  "signin": [
    "Sign In",
    "Log In",
    "Enter Account",
    "Access Account",
    "Member Login",
    "Account Entry",
    "User Access",
    "Sign On",
    "Login Now",
    "Member Sign In"
  ],
  "view_details": [
    "View Details",
    "See Details",
    "Product Info",
    "Learn More",
    "More Info",
    "Full Details",
    "Item Details",
    "Specifications",
    "Product Specs",
    "Description"
  ],
  "cart": [
    "Cart",
    "Basket",
    "Shopping Cart",
    "My Cart",
    "Your Basket",
    "Shopping Bag",
    "My Bag",
    "Cart Items",
    "Purchase Cart",
    "Order Basket"
  ],
  "see_more": [
    "See more",
    "View more",
    "Discover more",
    "Show more",
    "Explore further",
    "Check out more",
    "Read more",
    "Additional items",
    "View all",
    "More items"
  ],
  "shop_now": [
    "Shop now",
    "Browse now",
    "Start shopping",
    "Get started",
    "Begin browsing",
    "Shop today",
    "Visit store",
    "Explore store",
    "Start now",
    "Shop here"
  ],
  "cart_overview": [
    "Cart overview",
    "Cart summary",
    "Basket overview",
    "Your cart overview",
    "Shopping cart overview",
    "Order overview",
    "Cart snapshot",
    "Cart review",
    "Your basket overview",
    "Cart details"
  ],
  "shopping_cart": [
    "Shopping cart",
    "Your cart",
    "Cart",
    "Basket",
    "Shopping basket",
    "My cart",
    "My basket",
    "Cart items",
    "Basket items",
    "Cart summary"
  ],
  "cart_description": [
    "Review every item, quantity, and total before checkout.",
    "Check items, quantities, and totals before you pay.",
    "Confirm your items and totals before checkout.",
    "Review your cart and proceed when ready.",
    "Double-check quantities and totals before checkout.",
    "Verify your cart items and pricing.",
    "Review cart details before checkout.",
    "Confirm totals and quantities before paying.",
    "Make sure everything looks right before checkout.",
    "Review items and totals before continuing."
  ],
  "empty_cart": [
    "Your cart is empty",
    "Cart is empty",
    "No items in cart",
    "Nothing here yet",
    "Basket is empty",
    "Your basket is empty",
    "No items added",
    "Cart has no items",
    "Empty cart",
    "Start adding items"
  ],
  "empty_cart_message": [
    "Add items to see them here",
    "Add products to your cart to see them here",
    "Your items will appear here once added",
    "Start shopping to add items",
    "Add something to get started",
    "Browse products and add to cart",
    "Your selections will show up here",
    "Cart items will appear here",
    "No items yet — start shopping",
    "Add items and come back"
  ],
  "promo_code": [
    "Promo code",
    "Discount code",
    "Coupon code",
    "Promo",
    "Voucher code",
    "Offer code",
    "Savings code",
    "Code",
    "Promotion code",
    "Apply a code"
  ],
  "promo_placeholder": [
    "e.g. SAVE10",
    "e.g. WELCOME10",
    "e.g. DEALS5",
    "Enter code",
    "Type promo code",
    "Add promo code",
    "Have a code?",
    "Promo code",
    "Discount code",
    "Coupon"
  ],
  "apply": [
    "Apply",
    "Use",
    "Redeem",
    "Apply code",
    "Use code",
    "Confirm",
    "Add",
    "Submit",
    "Redeem code",
    "Apply coupon"
  ],
  "subtotal": [
    "Subtotal",
    "Items subtotal",
    "Cart subtotal",
    "Subtotal amount",
    "Pre-tax total",
    "Items total",
    "Sub total",
    "Estimated subtotal",
    "Current subtotal",
    "Subtotal value"
  ],
  "items": [
    "items",
    "item(s)",
    "products",
    "entries",
    "goods",
    "units",
    "lines",
    "cart items",
    "items total",
    "items count"
  ],
  "estimated_taxes": [
    "Estimated taxes",
    "Estimated tax",
    "Taxes (est.)",
    "Tax estimate",
    "Estimated VAT",
    "Estimated sales tax",
    "Estimated duties",
    "Taxes estimate",
    "Tax (estimated)",
    "Estimated tax amount"
  ],
  "estimated_tax": [
    "Estimated tax",
    "Estimated taxes",
    "Tax estimate",
    "Taxes (est.)",
    "Tax (estimated)",
    "Estimated sales tax",
    "Estimated VAT",
    "Estimated duties",
    "Tax amount (est.)",
    "Estimated tax total"
  ],
  "order_total": [
    "Order total",
    "Total",
    "Grand total",
    "Total due",
    "Total amount",
    "Final total",
    "Payable total",
    "Total payable",
    "Order amount",
    "Total to pay"
  ],
  "proceed_to_checkout": [
    "Checkout",
    "Proceed to checkout",
    "Go to checkout",
    "Continue to checkout",
    "Complete checkout",
    "Pay now",
    "Secure checkout",
    "Continue",
    "Checkout now",
    "Finalize purchase"
  ],
  "delivery_savings": [
    "Delivery savings",
    "Shipping savings",
    "Delivery offer",
    "Shipping offer",
    "Delivery deal",
    "Shipping deal",
    "Delivery perk",
    "Shipping perk",
    "Delivery benefit",
    "Shipping benefit"
  ],
  "qualifies_for_delivery": [
    "Your order qualifies for",
    "This order qualifies for",
    "You qualify for",
    "Your cart qualifies for",
    "Order qualifies for",
    "You’re eligible for",
    "This purchase qualifies for",
    "Your items qualify for",
    "You qualify for a",
    "Eligible for"
  ],
  "free_delivery": [
    "free delivery",
    "free shipping",
    "complimentary delivery",
    "complimentary shipping",
    "no-cost delivery",
    "no-cost shipping",
    "delivery on us",
    "shipping on us",
    "free dispatch",
    "free drop-off"
  ],
  "buyer_protection": [
    "Buyer protection",
    "Purchase protection",
    "Protected purchase",
    "Buyer coverage",
    "Order protection",
    "Protected order",
    "Coverage included",
    "Protection included",
    "Buyer guarantee",
    "Purchase guarantee"
  ],
  "fast_shipping": [
    "Fast shipping",
    "Fast delivery",
    "Quick shipping",
    "Quick delivery",
    "Express shipping",
    "Express delivery",
    "Rapid shipping",
    "Rapid delivery",
    "Speedy shipping",
    "Speedy delivery"
  ],
  "verified_partners": [
    "Verified partners",
    "Trusted partners",
    "Verified sellers",
    "Trusted sellers",
    "Verified vendors",
    "Trusted vendors",
    "Verified merchants",
    "Trusted merchants",
    "Verified providers",
    "Trusted providers"
  ],
  "unit": [
    "unit",
    "item",
    "each",
    "pc",
    "piece",
    "ea",
    "per item",
    "per unit",
    "per piece",
    "each unit"
  ],
  "view_product": [
    "View product",
    "View item",
    "Open product",
    "Open item",
    "See product",
    "See item",
    "Go to product",
    "Go to item",
    "View details",
    "Open details"
  ],
  "increase_quantity": [
    "Increase quantity",
    "Increase qty",
    "Add one",
    "Plus one",
    "Increase amount",
    "Raise quantity",
    "Increment quantity",
    "More",
    "Add",
    "Increase"
  ],
  "decrease_quantity": [
    "Decrease quantity",
    "Decrease qty",
    "Remove one",
    "Minus one",
    "Decrease amount",
    "Lower quantity",
    "Decrement quantity",
    "Less",
    "Remove",
    "Decrease"
  ],
  "qty": [
    "Qty",
    "Quantity",
    "Amount",
    "Count",
    "Units",
    "Pieces",
    "Number",
    "Qty.",
    "Item count",
    "Total units"
  ],
  "checkout_eyebrow": [
    "Checkout",
    "Secure checkout",
    "Review & pay",
    "Payment",
    "Finalize order",
    "Order checkout",
    "Confirm purchase",
    "Complete order",
    "Finish checkout",
    "Purchase"
  ],
  "checkout_description": [
    "Review your details and place your order.",
    "Confirm shipping and payment details to finish.",
    "Finalize your order details below.",
    "Double-check everything before placing your order.",
    "Complete delivery and payment information to proceed.",
    "Confirm and place your order securely.",
    "Review the order summary and submit your order.",
    "Check details and confirm purchase.",
    "Verify information and complete checkout.",
    "Finalize your purchase securely."
  ],
  "secure_checkout": [
    "Secure checkout",
    "Safe checkout",
    "Protected checkout",
    "Encrypted checkout",
    "Secure payment",
    "Safe payment",
    "Protected payment",
    "Secure ordering",
    "Checkout securely",
    "Secure purchase"
  ],
  "shipping_address": [
    "Shipping address",
    "Delivery address",
    "Ship to",
    "Where to deliver",
    "Shipping details",
    "Delivery details",
    "Address",
    "Delivery location",
    "Shipping location",
    "Recipient address"
  ],
  "billing_matches_shipping": [
    "Billing matches shipping",
    "Same as shipping address",
    "Billing address is the same",
    "Use shipping as billing",
    "Billing same as shipping",
    "Use shipping address",
    "Billing = shipping",
    "Use same address",
    "Copy shipping address",
    "Billing same address"
  ],
  "payment_method": [
    "Payment method",
    "Payment",
    "How you’ll pay",
    "Pay with",
    "Payment option",
    "Method of payment",
    "Payment type",
    "Choose payment",
    "Select payment",
    "Payment details"
  ],
  "review_order": [
    "Review order",
    "Review your order",
    "Order review",
    "Review items",
    "Confirm order",
    "Confirm items",
    "Review summary",
    "Check order",
    "Verify order",
    "Order confirmation"
  ],
  "review_and_confirm": [
    "Review & confirm",
    "Review and confirm",
    "Review & place order",
    "Confirm & pay",
    "Check & confirm",
    "Review details",
    "Confirm details",
    "Final review",
    "Review checkout",
    "Confirm purchase"
  ],
  "order_summary": [
    "Order summary",
    "Summary",
    "Order overview",
    "Purchase summary",
    "Checkout summary",
    "Order snapshot",
    "Order recap",
    "Summary of order",
    "Your summary",
    "Order details"
  ],
  "order_items": [
    "Order items",
    "Items",
    "Products",
    "Items in order",
    "Products in order",
    "Order contents",
    "Cart items",
    "Purchased items",
    "Items list",
    "Order list"
  ],
  "place_order": [
    "Place order",
    "Place your order",
    "Submit order",
    "Complete order",
    "Confirm order",
    "Finalize order",
    "Order now",
    "Pay now",
    "Buy now",
    "Complete purchase"
  ],
  "estimated_delivery": [
    "Estimated delivery",
    "Estimated arrival",
    "Delivery estimate",
    "Arrives by",
    "Expected delivery",
    "Expected arrival",
    "Estimated ship date",
    "Delivery window",
    "Estimated drop-off",
    "Estimated ETA"
  ],
  "shipping_handling": [
    "Shipping & handling",
    "Shipping and handling",
    "Delivery & handling",
    "Shipping",
    "Delivery",
    "Handling",
    "Shipping fees",
    "Delivery fees",
    "Shipping costs",
    "Delivery costs"
  ],
  "free": [
    "Free",
    "No cost",
    "Included",
    "$0",
    "Complimentary",
    "On us",
    "Gratis",
    "No charge",
    "Included free",
    "Free of charge"
  ],
  "free_shipping_banner": [
    "Free shipping on eligible orders",
    "Free delivery on eligible orders",
    "You qualify for free shipping",
    "You qualify for free delivery",
    "Free shipping available",
    "Free delivery available",
    "Shipping is free",
    "Delivery is free",
    "Enjoy free shipping",
    "Enjoy free delivery"
  ],
  "checkout_terms_prefix": [
    "By placing your order, you agree to the",
    "By continuing, you agree to the",
    "Placing an order means you accept the",
    "By checking out, you accept the",
    "By completing checkout, you agree to the",
    "By submitting, you agree to the",
    "By confirming, you agree to the",
    "By ordering, you agree to the",
    "By paying, you agree to the",
    "By proceeding, you agree to the"
  ],
  "terms_of_service": [
    "Terms of Service",
    "Terms",
    "Service terms",
    "Terms & conditions",
    "Conditions",
    "Terms of use",
    "Usage terms",
    "User terms",
    "Service conditions",
    "Terms and conditions"
  ],
  "privacy_policy": [
    "Privacy Policy",
    "Privacy",
    "Privacy notice",
    "Privacy statement",
    "Data policy",
    "Data privacy",
    "Privacy terms",
    "Privacy info",
    "Policy",
    "Privacy guidelines"
  ],
  "and": [
    "and",
    "&",
    "plus",
    "with",
    "along with",
    "as well as",
    "together with",
    "in addition to",
    "combined with",
    "as part of"
  ],
  "wishlist_title": [
    "Wishlist",
    "Your wishlist",
    "Saved items",
    "Favorites",
    "Saved for later",
    "My wishlist",
    "My saved items",
    "Your saved items",
    "My favorites",
    "Your favorites"
  ],
  "wishlist_description": [
    "Everything you flagged for later lives here.",
    "Your saved items live here for quick access.",
    "Items you saved for later appear here.",
    "Your favorites are collected here.",
    "Review saved items and move them to cart anytime.",
    "Keep track of products you like here.",
    "Saved picks appear here for later.",
    "Your wishlist is ready whenever you are.",
    "Items you saved show up here.",
    "Manage your saved items here."
  ],
  "wishlist_empty_title": [
    "No saved items yet",
    "Wishlist is empty",
    "No favorites yet",
    "Nothing saved yet",
    "No wishlist items",
    "No saved products",
    "Empty wishlist",
    "No items saved",
    "Start saving items",
    "Nothing in wishlist"
  ],
  "wishlist_empty_message": [
    "Save products to see them here.",
    "Add items to your wishlist to see them here.",
    "Start browsing and save items for later.",
    "Your saved items will appear here.",
    "Tap the heart to save items.",
    "Browse products and save your favorites.",
    "No saved items — start exploring.",
    "You haven’t saved anything yet.",
    "Start saving products you like.",
    "Save items and come back here."
  ],
  "wishlist": [
    "Wishlist",
    "Saved items",
    "Favorites",
    "Saved",
    "My wishlist",
    "My favorites",
    "Wish list",
    "Saved list",
    "Favorites list",
    "Wishlist items"
  ],
  "start_exploring": [
    "Start exploring",
    "Browse products",
    "Explore products",
    "Find products",
    "Discover items",
    "Shop now",
    "Start shopping",
    "Browse now",
    "Explore now",
    "Discover now"
  ],
  "clear_all": [
    "Clear all",
    "Remove all",
    "Delete all",
    "Clear everything",
    "Remove everything",
    "Empty list",
    "Reset",
    "Clear items",
    "Delete items",
    "Wipe all"
  ],
  "move_items_to_cart": [
    "Move items to cart",
    "Move to cart",
    "Add all to cart",
    "Send to cart",
    "Transfer to cart",
    "Move everything to cart",
    "Add items to cart",
    "Put in cart",
    "Add to basket",
    "Move to basket"
  ],
  "workflow_tips": [
    "Workflow tips",
    "Tips",
    "Helpful tips",
    "Quick tips",
    "Suggestions",
    "Pro tips",
    "Tips & tricks",
    "Notes",
    "Recommendations",
    "Hints"
  ],
  "snapshot": [
    "Snapshot",
    "Overview",
    "Summary",
    "At a glance",
    "Quick view",
    "Recap",
    "Summary view",
    "Quick summary",
    "Overview snapshot",
    "Status"
  ],
  "estimated_value": [
    "Estimated value",
    "Estimated total value",
    "Approximate value",
    "Estimated amount",
    "Approximate total",
    "Estimated worth",
    "Approx. value",
    "Estimated sum",
    "Approximate value total",
    "Estimated cart value"
  ],
  "order_timeline": [
    "Order timeline",
    "Timeline",
    "Order steps",
    "Checkout steps",
    "Order progress",
    "Progress",
    "Order flow",
    "Stages",
    "Steps",
    "Milestones"
  ],
  "added": [
    "Added",
    "Added to cart",
    "In cart",
    "Added ✓",
    "Done",
    "Saved to cart",
    "Added successfully",
    "Item added",
    "Added now",
    "Added!"
  ],
  "loading_product": [
    "Loading product",
    "Loading item",
    "Loading details",
    "Fetching product",
    "Please wait",
    "Loading…",
    "Getting product",
    "Preparing page",
    "Loading information",
    "Just a moment"
  ],
  "product_not_found": [
    "Product not found",
    "Item not found",
    "Not found",
    "Product unavailable",
    "Item unavailable",
    "We couldn't find that product",
    "This product is unavailable",
    "Missing product",
    "No product found",
    "Unavailable"
  ],
  "product_missing_message": [
    "The product you are looking for does not exist or has been removed.",
    "This item is no longer available.",
    "We couldn’t find this item.",
    "This product may have been removed.",
    "That product isn’t available anymore.",
    "This item may be out of catalog.",
    "Product unavailable at the moment.",
    "This listing is no longer active.",
    "We can’t locate that product.",
    "This product can’t be displayed."
  ],
  "return_to_home": [
    "Return to home",
    "Back to home",
    "Go home",
    "Home",
    "Return",
    "Back",
    "Back to shop",
    "Continue browsing",
    "Browse home",
    "Take me home"
  ],
  "share_success": [
    "Shared",
    "Shared successfully",
    "Sent",
    "Shared ✓",
    "Done",
    "Sent successfully",
    "Shared now",
    "Success",
    "Shared link",
    "Delivered"
  ],
  "link_copied": [
    "Link copied",
    "Copied",
    "Copied to clipboard",
    "Link saved",
    "Copied ✓",
    "Link copied ✓",
    "Saved",
    "Copied link",
    "Clipboard updated",
    "Copied now"
  ],
  "share_product": [
    "Share product",
    "Share",
    "Send",
    "Share this",
    "Send link",
    "Share item",
    "Send product",
    "Share details",
    "Share page",
    "Send page"
  ],
  "in_wishlist": [
    "In wishlist",
    "Saved",
    "In favorites",
    "Saved ✓",
    "Wishlisted",
    "In saved items",
    "In your wishlist",
    "Favorited",
    "Saved item",
    "In list"
  ],
  "add_to_wishlist": [
    "Add to wishlist",
    "Save",
    "Add to favorites",
    "Save for later",
    "Favorite",
    "Add to saved",
    "Save item",
    "Add to saved items",
    "Wishlist",
    "Add to list"
  ],
  "visit": [
    "Visit",
    "View",
    "Open",
    "Go to",
    "See",
    "Browse",
    "Check",
    "Explore",
    "Visit the",
    "View the"
  ],
  "store": [
    "Store",
    "Shop",
    "Brand store",
    "Storefront",
    "Shop page",
    "Brand page",
    "Store page",
    "Seller store",
    "Vendor store",
    "Marketplace"
  ],
  "why_shoppers_love": [
    "Why shoppers love it",
    "Highlights",
    "Top features",
    "Why you'll love it",
    "What stands out",
    "Key highlights",
    "Customer favorites",
    "Why it’s popular",
    "Why it’s loved",
    "Why it shines"
  ],
  "buy_new": [
    "Buy new",
    "New",
    "New item",
    "Buy new item",
    "New purchase",
    "New condition",
    "Brand new",
    "Buy brand new",
    "New listing",
    "Buy new condition"
  ],
  "deliver_to": [
    "Deliver to",
    "Ship to",
    "Delivering to",
    "Shipping to",
    "Send to",
    "Deliver at",
    "Ship at",
    "Deliver here",
    "Ship here",
    "Deliver destination"
  ],
  "free_delivery_label": [
    "Free delivery",
    "Free shipping",
    "Delivery included",
    "Shipping included",
    "No-cost delivery",
    "No-cost shipping",
    "Complimentary delivery",
    "Complimentary shipping",
    "Delivery on us",
    "Shipping on us"
  ],
  "courier_partners": [
    "Autozone courier partners",
    "Courier partners",
    "Delivery partners",
    "Shipping partners",
    "Trusted couriers",
    "Carrier partners",
    "Delivery network",
    "Partner couriers",
    "Fulfillment partners",
    "Shipping network"
  ],
  "ships_from": [
    "Ships from",
    "Shipped from",
    "Dispatches from",
    "Fulfilled from",
    "From",
    "Origin",
    "Shipping origin",
    "Dispatch origin",
    "Fulfillment origin",
    "Ships out of"
  ],
  "autozone_fulfillment": [
    "Autozone Fulfillment",
    "Autozone warehouse",
    "Autozone distribution",
    "Autozone logistics",
    "Autozone shipping",
    "Autozone fulfillment center",
    "Autozone dispatch",
    "Autozone DC",
    "Autozone hub",
    "Autozone fulfillment"
  ],
  "sold_by": [
    "Sold by",
    "Seller",
    "Provided by",
    "From seller",
    "Vendor",
    "Merchant",
    "Retailer",
    "Supplied by",
    "Offered by",
    "Sold via"
  ],
  "verified_partner": [
    "Verified Partner",
    "Verified seller",
    "Trusted partner",
    "Trusted seller",
    "Verified vendor",
    "Authorized partner",
    "Certified partner",
    "Verified merchant",
    "Trusted merchant",
    "Verified provider"
  ],
  "returns": [
    "Returns",
    "Return policy",
    "Returns policy",
    "Easy returns",
    "Return options",
    "Refunds & returns",
    "Return details",
    "Return window",
    "Returns info",
    "Return terms"
  ],
  "returns_policy": [
    "30-day refund policy",
    "30-day returns",
    "30-day return policy",
    "Free returns within 30 days",
    "Return within 30 days",
    "30 days to return",
    "Refunds within 30 days",
    "30-day refunds",
    "Easy 30-day returns",
    "30-day return window"
  ],
  "payment": [
    "Payment",
    "Payment info",
    "Payment details",
    "Pay",
    "Paying",
    "Payment method",
    "Checkout payment",
    "Transaction",
    "Payment options",
    "How you pay"
  ],
  "secure_transaction": [
    "Secure transaction",
    "Secure payment",
    "Encrypted transaction",
    "Protected payment",
    "Secure checkout",
    "Safe transaction",
    "Protected transaction",
    "Secure processing",
    "Safe payment",
    "Secure purchase"
  ],
  "shipping_options": [
    "Shipping options",
    "Delivery options",
    "Shipping choices",
    "Delivery choices",
    "Shipping methods",
    "Delivery methods",
    "Shipping",
    "Delivery",
    "Shipping details",
    "Delivery details"
  ],
  "collapse": [
    "Collapse",
    "Close",
    "Hide",
    "Show less",
    "Minimize",
    "Fold",
    "Collapse section",
    "Close details",
    "Hide details",
    "Less"
  ],
  "expand": [
    "Expand",
    "Open",
    "Show more",
    "Show details",
    "See more",
    "Reveal",
    "Expand section",
    "Open details",
    "More",
    "Details"
  ],
  "shipping_bullet_1": [
    "Choose standard, expedited, or same-day when available.",
    "Pick standard, express, or same-day options when available.",
    "Select from standard or faster delivery options.",
    "Choose your delivery speed at checkout.",
    "Delivery speed options may be available.",
    "Standard and faster shipping may be available.",
    "Choose the delivery option that fits you.",
    "Select a shipping option when available.",
    "Choose standard or expedited when available.",
    "Multiple delivery options may be available."
  ],
  "shipping_bullet_2": [
    "Free returns within 30 days on most items.",
    "Most items can be returned within 30 days.",
    "Easy returns within 30 days.",
    "30-day returns on eligible items.",
    "Return eligible items within 30 days.",
    "Free returns available on most items.",
    "Returns accepted within 30 days.",
    "30-day return window on most items.",
    "Free returns on eligible purchases.",
    "Return within 30 days on most items."
  ],
  "shipping_bullet_3": [
    "Bundle matching accessories for automatic discounts.",
    "Bundle accessories to unlock discounts.",
    "Add matching accessories to save automatically.",
    "Combine accessories for extra savings.",
    "Bundle add-ons for discounts.",
    "Pair accessories to unlock deals.",
    "Bundle compatible items for savings.",
    "Add bundles for automatic discounts.",
    "Bundle items for better pricing.",
    "Combine add-ons for savings."
  ],
  "add_gift_receipt": [
    "Add gift receipt",
    "Include gift receipt",
    "Gift receipt",
    "Add receipt",
    "Include receipt",
    "Add gift note",
    "Include gift note",
    "Gift receipt option",
    "Add gift option",
    "Include gift option"
  ],
  "about_this_item": [
    "About this item",
    "About the item",
    "About this product",
    "Item details",
    "Product overview",
    "Details",
    "About",
    "What to know",
    "Item overview",
    "Product details"
  ],
  "product_details": [
    "Product details",
    "Details",
    "Product info",
    "Item details",
    "Information",
    "Specifications",
    "More details",
    "Full details",
    "Product overview",
    "About"
  ],
  "product_details_description": [
    "What shoppers and our product team call out before you add it to cart.",
    "Key details to know before you add it to your cart.",
    "Highlights our team and shoppers mention before purchase.",
    "Important details to review before checkout.",
    "What to know before you buy.",
    "Key notes before you add to cart.",
    "Details to help you decide quickly.",
    "What stands out before you purchase.",
    "The essentials before adding to cart.",
    "Key callouts before you check out."
  ],
  "all_categories": [
    "All categories",
    "All Categories",
    "Browse All",
    "View All",
    "All",
    "Categories",
    "Shop All",
    "All Items",
    "Browse Categories",
    "View Categories"
  ],
  "finalize_order": [
    "Finalize order",
    "Place Order",
    "Complete Order",
    "Confirm Order",
    "Submit Order",
    "Finish Order",
    "Order Now",
    "Checkout",
    "Place Order",
    "Confirm Purchase"
  ]
}
